CHANGES.txt
CREDITS.txt
LICENSE.txt
MANIFEST.in
README.md
TODO.sh
setup.py
doc/.natu.pws
doc/BIPM-ini.rst
doc/README.md
doc/api.rst
doc/base-ini.rst
doc/changes.rst
doc/conf.py
doc/credits.rst
doc/definitions.rst
doc/derived-ini.rst
doc/index.rst
doc/install.rst
doc/license.rst
doc/make.py
doc/natu.config.rst
doc/natu.core.rst
doc/natu.exponents.rst
doc/natu.groups.acceleration.rst
doc/natu.groups.amount.rst
doc/natu.groups.angle.rst
doc/natu.groups.area.rst
doc/natu.groups.charge.rst
doc/natu.groups.conductance.rst
doc/natu.groups.constants.rst
doc/natu.groups.current.rst
doc/natu.groups.dimensionless.rst
doc/natu.groups.energy.rst
doc/natu.groups.force.rst
doc/natu.groups.frequency.rst
doc/natu.groups.length.rst
doc/natu.groups.magnetic_flux.rst
doc/natu.groups.magnetic_flux_density.rst
doc/natu.groups.mass.rst
doc/natu.groups.potential.rst
doc/natu.groups.power.rst
doc/natu.groups.pressure.rst
doc/natu.groups.resistance.rst
doc/natu.groups.rst
doc/natu.groups.si.rst
doc/natu.groups.temperature.rst
doc/natu.groups.time.rst
doc/natu.groups.velocity.rst
doc/natu.groups.volume.rst
doc/natu.math.rst
doc/natu.numpy.rst
doc/natu.pws
doc/natu.units.rst
doc/natu.util.rst
doc/other-ini.rst
doc/seealso.rst
doc/usermodules.rst
doc/_static/analytics.js
doc/_static/copybutton.js
doc/_static/custom.css
doc/_static/favicon-160x160.png
doc/_static/favicon-16x16.png
doc/_static/favicon-196x196.png
doc/_static/favicon-32x32.png
doc/_static/favicon-96x96.png
doc/_static/favicon.ico
doc/_static/favicon.svg
doc/_static/hspace.png
doc/_static/logo.svg
doc/_templates/api.html
doc/_templates/definitions.html
doc/_templates/download.html
doc/_templates/globaltoc.html
doc/_templates/info.html
doc/_templates/layout.html
doc/_templates/links.html
doc/_templates/search.html
doc/_templates/searchbox.html
doc/_templates/user.html
doc/extra/googledadb6c37b51fb2dc.html
natu/__init__.py
natu/_decorators.py
natu/_prefixes.py
natu/core.py
natu/exponents.py
natu/math.py
natu/numpy.py
natu/units.py
natu.egg-info/PKG-INFO
natu.egg-info/SOURCES.txt
natu.egg-info/dependency_links.txt
natu.egg-info/not-zip-safe
natu.egg-info/top_level.txt
