Metadata-Version: 1.1
Name: natu
Version: 0.1.0-a5
Summary: Natural units in Python
Home-page: http://kdavies4.github.io/natu/
Author: Kevin Davies
Author-email: kdavies4@gmail.com
License: BSD-compatible (see LICENSE.txt)
Download-URL: https://github.com/kdavies4/natu/archive/v0.1.0-a5.zip
Keywords: quantity calculus quantities unit conversion natural SI CGS Planck Hartree
Platform: any
Classifier: Development Status :: 3 - Alpha
Classifier: Intended Audience :: Science/Research
Classifier: Intended Audience :: Education
Classifier: Topic :: Scientific/Engineering
Classifier: Topic :: Software Development :: Quality Assurance
Classifier: License :: OSI Approved :: BSD License
Classifier: Programming Language :: Python :: 2.7
Classifier: Programming Language :: Python :: 3.2
Classifier: Programming Language :: Python :: 3.3
Classifier: Programming Language :: Python :: 3.4
Classifier: Operating System :: POSIX :: Linux
Classifier: Operating System :: Microsoft :: Windows
Provides: natu
